{
    "name": "Домашние задания 10 Б",
    "short_name": "Домашние задания 10 Б",
    "description": "Домашние задания 10 Б",
    "icons": [
        {
            "src": "./assets/images/c10b32.jpg",
            "sizes": "32x32",
            "type": "image/jpg"
        },
        {
            "src": "./assets/images/c10b144.jpg",
            "sizes": "144x144",
            "type": "image/jpg"
        },
        {
            "src": "./assets/images/c10b512.jpg",
            "sizes": "512x512",
            "type": "image/jpg"
        }
    ],
    "start_url": ".",
    "display": "fullscreen",
    "theme_color": "#ffffff",
    "background_color": "#ffffff"
}

